internal_token_service/__init__.py
internal_token_service/main.py
internal_token_service-0.5.dist-info/LICENSE.txt
internal_token_service-0.5.dist-info/METADATA
internal_token_service-0.5.dist-info/WHEEL
internal_token_service-0.5.dist-info/top_level.txt
internal_token_service-0.5.dist-info/RECORD
