Metadata-Version: 2.1
Name: internal-token-service
Version: 0.5
Summary: UNKNOWN
Home-page: UNKNOWN
License: MIT
Platform: UNKNOWN
Requires-Dist: PyJWT (>=2.0.0)
